{
  "Top": "ipv4_top",
  "RtlTop": "ipv4_top",
  "RtlPrefix": "",
  "RtlSubPrefix": "ipv4_top_",
  "SourceLanguage": "cpp",
  "HostMachineBits": "64",
  "FunctionProtocol": "ap_ctrl_none",
  "ResetStyle": "control",
  "Target": {
    "Family": "virtexuplushbm",
    "Device": "xcu280",
    "Package": "-fsvh2892",
    "Speed": "-2L-e",
    "Triple": "fpga64-xilinx-none"
  },
  "Args": {
    "s_axis_rx_data": {
      "index": "0",
      "direction": "in",
      "srcType": "stream<hls::axis<ap_uint<512>, 0, 0, 0>, 0>&",
      "srcSize": "1024",
      "hwRefs": [{
          "type": "interface",
          "interface": "s_axis_rx_data",
          "name": "",
          "usage": "data",
          "direction": "in"
        }]
    },
    "m_axis_rx_meta": {
      "index": "1",
      "direction": "out",
      "srcType": "stream<ipv4Meta, 0>&",
      "srcSize": "64",
      "hwRefs": [{
          "type": "interface",
          "interface": "m_axis_rx_meta",
          "name": "",
          "usage": "data",
          "direction": "out"
        }]
    },
    "m_axis_rx_data": {
      "index": "2",
      "direction": "out",
      "srcType": "stream<hls::axis<ap_uint<512>, 0, 0, 0>, 0>&",
      "srcSize": "1024",
      "hwRefs": [{
          "type": "interface",
          "interface": "m_axis_rx_data",
          "name": "",
          "usage": "data",
          "direction": "out"
        }]
    },
    "s_axis_tx_meta": {
      "index": "3",
      "direction": "in",
      "srcType": "stream<ipv4Meta, 0>&",
      "srcSize": "64",
      "hwRefs": [{
          "type": "interface",
          "interface": "s_axis_tx_meta",
          "name": "",
          "usage": "data",
          "direction": "in"
        }]
    },
    "s_axis_tx_data": {
      "index": "4",
      "direction": "in",
      "srcType": "stream<hls::axis<ap_uint<512>, 0, 0, 0>, 0>&",
      "srcSize": "1024",
      "hwRefs": [{
          "type": "interface",
          "interface": "s_axis_tx_data",
          "name": "",
          "usage": "data",
          "direction": "in"
        }]
    },
    "m_axis_tx_data": {
      "index": "5",
      "direction": "out",
      "srcType": "stream<hls::axis<ap_uint<512>, 0, 0, 0>, 0>&",
      "srcSize": "1024",
      "hwRefs": [{
          "type": "interface",
          "interface": "m_axis_tx_data",
          "name": "",
          "usage": "data",
          "direction": "out"
        }]
    },
    "local_ipv4_address": {
      "index": "6",
      "direction": "in",
      "srcType": "ap_uint<32>",
      "srcSize": "32",
      "hwRefs": [{
          "type": "port",
          "interface": "local_ipv4_address",
          "name": "local_ipv4_address",
          "usage": "data",
          "direction": "in"
        }]
    },
    "protocol": {
      "index": "7",
      "direction": "in",
      "srcType": "ap_uint<8>",
      "srcSize": "8",
      "hwRefs": [{
          "type": "port",
          "interface": "protocol",
          "name": "protocol",
          "usage": "data",
          "direction": "in"
        }]
    }
  },
  "HlsSolution": {
    "FlowTarget": "vivado",
    "ConfigTcl": [
      "config_export -description=-display_name=IPv4",
      "config_export -format=ip_catalog",
      "config_export -ipname=ipv4",
      "config_export -vendor=ethz.systems.fpga",
      "config_export -version=0.1"
    ],
    "ProfileOption": "0",
    "ProfileType": "none",
    "KernelName": "ipv4_top"
  },
  "ClockInfo": {
    "ClockName": "ap_clk",
    "ClockPeriod": "3.2",
    "Uncertainty": "0.864",
    "IsCombinational": "0",
    "II": "1",
    "Latency": "6"
  },
  "Xdc": {"OocClocks": ["create_clock -name ap_clk -period 3.200 [get_ports ap_clk]"]},
  "Ipx": {
    "Vendor": "ethz.systems.fpga",
    "Library": "hls",
    "Name": "ipv4",
    "Version": "0.1",
    "DisplayName": "IPv4",
    "Revision": "",
    "Description": "An IP generated by Vitis HLS",
    "Taxonomy": "\/VITIS_HLS_IP",
    "AutoFamilySupport": "",
    "ZipFile": "ethz_systems_fpga_hls_ipv4_0_1.zip"
  },
  "Files": {
    "CSource": ["\/home\/yangz0e\/Desktop\/Vitis_with_100Gbps_TCP-IP_top_k\/fpga-network-stack\/hls\/ipv4\/ipv4.cpp"],
    "Vhdl": [
      "impl\/vhdl\/ipv4_top_convert_axis_to_net_axis_512_1.vhd",
      "impl\/vhdl\/ipv4_top_convert_axis_to_net_axis_512_s.vhd",
      "impl\/vhdl\/ipv4_top_convert_net_axis_to_axis_512_1.vhd",
      "impl\/vhdl\/ipv4_top_convert_net_axis_to_axis_512_s.vhd",
      "impl\/vhdl\/ipv4_top_entry_proc.vhd",
      "impl\/vhdl\/ipv4_top_fifo_w4_d2_S.vhd",
      "impl\/vhdl\/ipv4_top_fifo_w8_d4_S.vhd",
      "impl\/vhdl\/ipv4_top_fifo_w32_d4_S.vhd",
      "impl\/vhdl\/ipv4_top_fifo_w1024_d2_S.vhd",
      "impl\/vhdl\/ipv4_top_fifo_w1024_d8_A.vhd",
      "impl\/vhdl\/ipv4_top_ipv4_drop_optional_ip_header_512_s.vhd",
      "impl\/vhdl\/ipv4_top_ipv4_generate_ipv4_512_s.vhd",
      "impl\/vhdl\/ipv4_top_ipv4_lshiftWordByOctet_512_2_s.vhd",
      "impl\/vhdl\/ipv4_top_process_ipv4_512_s.vhd",
      "impl\/vhdl\/ipv4_top_regslice_both.vhd",
      "impl\/vhdl\/ipv4_top.vhd"
    ],
    "Verilog": [
      "impl\/verilog\/ipv4_top_convert_axis_to_net_axis_512_1.v",
      "impl\/verilog\/ipv4_top_convert_axis_to_net_axis_512_s.v",
      "impl\/verilog\/ipv4_top_convert_net_axis_to_axis_512_1.v",
      "impl\/verilog\/ipv4_top_convert_net_axis_to_axis_512_s.v",
      "impl\/verilog\/ipv4_top_entry_proc.v",
      "impl\/verilog\/ipv4_top_fifo_w4_d2_S.v",
      "impl\/verilog\/ipv4_top_fifo_w8_d4_S.v",
      "impl\/verilog\/ipv4_top_fifo_w32_d4_S.v",
      "impl\/verilog\/ipv4_top_fifo_w1024_d2_S.v",
      "impl\/verilog\/ipv4_top_fifo_w1024_d8_A.v",
      "impl\/verilog\/ipv4_top_hls_deadlock_detection_unit.v",
      "impl\/verilog\/ipv4_top_hls_deadlock_detector.vh",
      "impl\/verilog\/ipv4_top_hls_deadlock_idx0_monitor.v",
      "impl\/verilog\/ipv4_top_hls_deadlock_kernel_monitor_top.vh",
      "impl\/verilog\/ipv4_top_hls_deadlock_report_unit.vh",
      "impl\/verilog\/ipv4_top_ipv4_drop_optional_ip_header_512_s.v",
      "impl\/verilog\/ipv4_top_ipv4_generate_ipv4_512_s.v",
      "impl\/verilog\/ipv4_top_ipv4_lshiftWordByOctet_512_2_s.v",
      "impl\/verilog\/ipv4_top_process_ipv4_512_s.v",
      "impl\/verilog\/ipv4_top_regslice_both.v",
      "impl\/verilog\/ipv4_top.v"
    ],
    "IpMisc": ["impl\/misc\/logo.png"],
    "CsynthXml": "syn\/report\/csynth.xml",
    "DebugDir": ".debug",
    "KernelXml": ".autopilot\/db\/kernel.internal.xml",
    "Xo": "",
    "XoHlsDir": "",
    "ProtoInst": [".debug\/ipv4_top.protoinst"]
  },
  "SubcoreInfo": {
    "HasXpmMemory": false,
    "HasClockedDsp": false,
    "Ip": []
  },
  "Interfaces": {
    "ap_clk": {
      "type": "clock",
      "busTypeName": "clock",
      "mode": "slave",
      "busParams": {
        "ASSOCIATED_BUSIF": "s_axis_rx_data:m_axis_rx_meta:m_axis_rx_data:s_axis_tx_meta:s_axis_tx_data:m_axis_tx_data",
        "ASSOCIATED_RESET": "ap_rst_n"
      },
      "portMap": {"ap_clk": "CLK"},
      "ports": ["ap_clk"]
    },
    "ap_rst_n": {
      "type": "reset",
      "busTypeName": "reset",
      "mode": "slave",
      "busParams": {"POLARITY": "ACTIVE_LOW"},
      "portMap": {"ap_rst_n": "RST"},
      "ports": ["ap_rst_n"]
    },
    "s_axis_rx_data": {
      "type": "axi4stream",
      "busTypeName": "axis",
      "mode": "slave",
      "dataWidth": "512",
      "portPrefix": "s_axis_rx_data_",
      "ports": [
        "s_axis_rx_data_TDATA",
        "s_axis_rx_data_TKEEP",
        "s_axis_rx_data_TLAST",
        "s_axis_rx_data_TREADY",
        "s_axis_rx_data_TSTRB",
        "s_axis_rx_data_TVALID"
      ],
      "constraints": [{
          "constraint_type": "pragma interface",
          "mode": "axis",
          "register_option": "1",
          "register_mode": "both",
          "argName": "s_axis_rx_data"
        }]
    },
    "m_axis_rx_meta": {
      "type": "axi4stream",
      "busTypeName": "axis",
      "mode": "master",
      "dataWidth": "48",
      "portPrefix": "m_axis_rx_meta_",
      "ports": [
        "m_axis_rx_meta_TDATA",
        "m_axis_rx_meta_TREADY",
        "m_axis_rx_meta_TVALID"
      ],
      "constraints": [{
          "constraint_type": "pragma interface",
          "mode": "axis",
          "register_option": "1",
          "register_mode": "both",
          "argName": "m_axis_rx_meta"
        }]
    },
    "m_axis_rx_data": {
      "type": "axi4stream",
      "busTypeName": "axis",
      "mode": "master",
      "dataWidth": "512",
      "portPrefix": "m_axis_rx_data_",
      "ports": [
        "m_axis_rx_data_TDATA",
        "m_axis_rx_data_TKEEP",
        "m_axis_rx_data_TLAST",
        "m_axis_rx_data_TREADY",
        "m_axis_rx_data_TSTRB",
        "m_axis_rx_data_TVALID"
      ],
      "constraints": [{
          "constraint_type": "pragma interface",
          "mode": "axis",
          "register_option": "1",
          "register_mode": "both",
          "argName": "m_axis_rx_data"
        }]
    },
    "s_axis_tx_meta": {
      "type": "axi4stream",
      "busTypeName": "axis",
      "mode": "slave",
      "dataWidth": "48",
      "portPrefix": "s_axis_tx_meta_",
      "ports": [
        "s_axis_tx_meta_TDATA",
        "s_axis_tx_meta_TREADY",
        "s_axis_tx_meta_TVALID"
      ],
      "constraints": [{
          "constraint_type": "pragma interface",
          "mode": "axis",
          "register_option": "1",
          "register_mode": "both",
          "argName": "s_axis_tx_meta"
        }]
    },
    "s_axis_tx_data": {
      "type": "axi4stream",
      "busTypeName": "axis",
      "mode": "slave",
      "dataWidth": "512",
      "portPrefix": "s_axis_tx_data_",
      "ports": [
        "s_axis_tx_data_TDATA",
        "s_axis_tx_data_TKEEP",
        "s_axis_tx_data_TLAST",
        "s_axis_tx_data_TREADY",
        "s_axis_tx_data_TSTRB",
        "s_axis_tx_data_TVALID"
      ],
      "constraints": [{
          "constraint_type": "pragma interface",
          "mode": "axis",
          "register_option": "1",
          "register_mode": "both",
          "argName": "s_axis_tx_data"
        }]
    },
    "m_axis_tx_data": {
      "type": "axi4stream",
      "busTypeName": "axis",
      "mode": "master",
      "dataWidth": "512",
      "portPrefix": "m_axis_tx_data_",
      "ports": [
        "m_axis_tx_data_TDATA",
        "m_axis_tx_data_TKEEP",
        "m_axis_tx_data_TLAST",
        "m_axis_tx_data_TREADY",
        "m_axis_tx_data_TSTRB",
        "m_axis_tx_data_TVALID"
      ],
      "constraints": [{
          "constraint_type": "pragma interface",
          "mode": "axis",
          "register_option": "1",
          "register_mode": "both",
          "argName": "m_axis_tx_data"
        }]
    },
    "local_ipv4_address": {
      "type": "data",
      "busTypeName": "data",
      "protocol": "ap_none",
      "mode": "slave",
      "dataWidth": "32",
      "portMap": {"local_ipv4_address": "DATA"},
      "ports": ["local_ipv4_address"],
      "constraints": [{
          "constraint_type": "pragma interface",
          "mode": "ap_none",
          "register_option": "1",
          "argName": "local_ipv4_address"
        }]
    },
    "protocol": {
      "type": "data",
      "busTypeName": "data",
      "protocol": "ap_none",
      "mode": "slave",
      "dataWidth": "8",
      "portMap": {"protocol": "DATA"},
      "ports": ["protocol"],
      "constraints": [{
          "constraint_type": "pragma interface",
          "mode": "ap_none",
          "register_option": "1",
          "argName": "protocol"
        }]
    }
  },
  "RtlPorts": {
    "ap_local_block": {
      "dir": "out",
      "width": "1",
      "isVector": "true"
    },
    "ap_local_deadlock": {
      "dir": "out",
      "width": "1",
      "isVector": "true"
    },
    "ap_clk": {
      "dir": "in",
      "width": "1"
    },
    "ap_rst_n": {
      "dir": "in",
      "width": "1"
    },
    "s_axis_rx_data_TDATA": {
      "dir": "in",
      "width": "512"
    },
    "s_axis_rx_data_TKEEP": {
      "dir": "in",
      "width": "64"
    },
    "s_axis_rx_data_TSTRB": {
      "dir": "in",
      "width": "64"
    },
    "s_axis_rx_data_TLAST": {
      "dir": "in",
      "width": "1",
      "isVector": "true"
    },
    "s_axis_rx_data_TVALID": {
      "dir": "in",
      "width": "1"
    },
    "s_axis_rx_data_TREADY": {
      "dir": "out",
      "width": "1"
    },
    "m_axis_rx_meta_TDATA": {
      "dir": "out",
      "width": "48"
    },
    "m_axis_rx_meta_TVALID": {
      "dir": "out",
      "width": "1"
    },
    "m_axis_rx_meta_TREADY": {
      "dir": "in",
      "width": "1"
    },
    "m_axis_rx_data_TDATA": {
      "dir": "out",
      "width": "512"
    },
    "m_axis_rx_data_TKEEP": {
      "dir": "out",
      "width": "64"
    },
    "m_axis_rx_data_TSTRB": {
      "dir": "out",
      "width": "64"
    },
    "m_axis_rx_data_TLAST": {
      "dir": "out",
      "width": "1",
      "isVector": "true"
    },
    "m_axis_rx_data_TVALID": {
      "dir": "out",
      "width": "1"
    },
    "m_axis_rx_data_TREADY": {
      "dir": "in",
      "width": "1"
    },
    "s_axis_tx_meta_TDATA": {
      "dir": "in",
      "width": "48"
    },
    "s_axis_tx_meta_TVALID": {
      "dir": "in",
      "width": "1"
    },
    "s_axis_tx_meta_TREADY": {
      "dir": "out",
      "width": "1"
    },
    "s_axis_tx_data_TDATA": {
      "dir": "in",
      "width": "512"
    },
    "s_axis_tx_data_TKEEP": {
      "dir": "in",
      "width": "64"
    },
    "s_axis_tx_data_TSTRB": {
      "dir": "in",
      "width": "64"
    },
    "s_axis_tx_data_TLAST": {
      "dir": "in",
      "width": "1",
      "isVector": "true"
    },
    "s_axis_tx_data_TVALID": {
      "dir": "in",
      "width": "1"
    },
    "s_axis_tx_data_TREADY": {
      "dir": "out",
      "width": "1"
    },
    "m_axis_tx_data_TDATA": {
      "dir": "out",
      "width": "512"
    },
    "m_axis_tx_data_TKEEP": {
      "dir": "out",
      "width": "64"
    },
    "m_axis_tx_data_TSTRB": {
      "dir": "out",
      "width": "64"
    },
    "m_axis_tx_data_TLAST": {
      "dir": "out",
      "width": "1",
      "isVector": "true"
    },
    "m_axis_tx_data_TVALID": {
      "dir": "out",
      "width": "1"
    },
    "m_axis_tx_data_TREADY": {
      "dir": "in",
      "width": "1"
    },
    "local_ipv4_address": {
      "dir": "in",
      "width": "32"
    },
    "protocol": {
      "dir": "in",
      "width": "8"
    }
  },
  "ModuleInfo": {
    "Hierarchy": {
      "ModuleName": "ipv4_top",
      "Instances": [
        {
          "ModuleName": "entry_proc",
          "InstanceName": "entry_proc_U0"
        },
        {
          "ModuleName": "convert_axis_to_net_axis_512_s",
          "InstanceName": "convert_axis_to_net_axis_512_U0"
        },
        {
          "ModuleName": "convert_axis_to_net_axis_512_1",
          "InstanceName": "convert_axis_to_net_axis_512_1_U0"
        },
        {
          "ModuleName": "convert_net_axis_to_axis_512_s",
          "InstanceName": "convert_net_axis_to_axis_512_U0"
        },
        {
          "ModuleName": "convert_net_axis_to_axis_512_1",
          "InstanceName": "convert_net_axis_to_axis_512_1_U0"
        },
        {
          "ModuleName": "process_ipv4_512_s",
          "InstanceName": "process_ipv4_512_U0"
        },
        {
          "ModuleName": "ipv4_lshiftWordByOctet_512_2_s",
          "InstanceName": "ipv4_lshiftWordByOctet_512_2_U0"
        },
        {
          "ModuleName": "ipv4_drop_optional_ip_header_512_s",
          "InstanceName": "ipv4_drop_optional_ip_header_512_U0"
        },
        {
          "ModuleName": "ipv4_generate_ipv4_512_s",
          "InstanceName": "ipv4_generate_ipv4_512_U0"
        }
      ]
    },
    "Info": {
      "entry_proc": {
        "FunctionProtocol": "ap_ctrl_hs",
        "isTaskLevelControl": "0",
        "isPipelined": "0",
        "isCombinational": "0",
        "isOneStateSeq": "1"
      },
      "convert_axis_to_net_axis_512_s": {
        "FunctionProtocol": "ap_ctrl_hs",
        "isTaskLevelControl": "0",
        "isPipelined": "1",
        "isCombinational": "0",
        "isOneStateSeq": "0"
      },
      "convert_axis_to_net_axis_512_1": {
        "FunctionProtocol": "ap_ctrl_hs",
        "isTaskLevelControl": "0",
        "isPipelined": "1",
        "isCombinational": "0",
        "isOneStateSeq": "0"
      },
      "convert_net_axis_to_axis_512_s": {
        "FunctionProtocol": "ap_ctrl_hs",
        "isTaskLevelControl": "0",
        "isPipelined": "1",
        "isCombinational": "0",
        "isOneStateSeq": "0"
      },
      "convert_net_axis_to_axis_512_1": {
        "FunctionProtocol": "ap_ctrl_hs",
        "isTaskLevelControl": "0",
        "isPipelined": "1",
        "isCombinational": "0",
        "isOneStateSeq": "0"
      },
      "process_ipv4_512_s": {
        "FunctionProtocol": "ap_ctrl_hs",
        "isTaskLevelControl": "0",
        "isPipelined": "1",
        "isCombinational": "0",
        "isOneStateSeq": "0"
      },
      "ipv4_drop_optional_ip_header_512_s": {
        "FunctionProtocol": "ap_ctrl_hs",
        "isTaskLevelControl": "0",
        "isPipelined": "1",
        "isCombinational": "0",
        "isOneStateSeq": "0"
      },
      "ipv4_lshiftWordByOctet_512_2_s": {
        "FunctionProtocol": "ap_ctrl_hs",
        "isTaskLevelControl": "0",
        "isPipelined": "1",
        "isCombinational": "0",
        "isOneStateSeq": "0"
      },
      "ipv4_generate_ipv4_512_s": {
        "FunctionProtocol": "ap_ctrl_hs",
        "isTaskLevelControl": "0",
        "isPipelined": "1",
        "isCombinational": "0",
        "isOneStateSeq": "0"
      },
      "ipv4_top": {
        "FunctionProtocol": "ap_ctrl_none",
        "isTaskLevelControl": "0",
        "isPipelined": "1",
        "isCombinational": "0",
        "isOneStateSeq": "0"
      }
    },
    "Metrics": {
      "entry_proc": {
        "Latency": {
          "LatencyBest": "0",
          "LatencyAvg": "0",
          "LatencyWorst": "0",
          "PipelineII": "0",
          "PipelineDepth": "",
          "PipelineType": "no"
        },
        "Timing": {
          "Target": "3.20",
          "Uncertainty": "0.86",
          "Estimate": "1.168"
        },
        "Area": {
          "FF": "2",
          "AVAIL_FF": "2607360",
          "UTIL_FF": "~0",
          "LUT": "29",
          "AVAIL_LUT": "1303680",
          "UTIL_LUT": "~0",
          "BRAM_18K": "0",
          "AVAIL_BRAM": "4032",
          "UTIL_BRAM": "0",
          "DSP": "0",
          "AVAIL_DSP": "9024",
          "UTIL_DSP": "0",
          "URAM": "0",
          "AVAIL_URAM": "960",
          "UTIL_URAM": "0"
        }
      },
      "convert_axis_to_net_axis_512_s": {
        "Latency": {
          "LatencyBest": "1",
          "LatencyAvg": "1",
          "LatencyWorst": "1",
          "PipelineII": "1",
          "PipelineDepth": "2",
          "PipelineType": "yes"
        },
        "Timing": {
          "Target": "3.20",
          "Uncertainty": "0.86",
          "Estimate": "1.168"
        },
        "Area": {
          "FF": "581",
          "AVAIL_FF": "2607360",
          "UTIL_FF": "~0",
          "LUT": "37",
          "AVAIL_LUT": "1303680",
          "UTIL_LUT": "~0",
          "BRAM_18K": "0",
          "AVAIL_BRAM": "4032",
          "UTIL_BRAM": "0",
          "DSP": "0",
          "AVAIL_DSP": "9024",
          "UTIL_DSP": "0",
          "URAM": "0",
          "AVAIL_URAM": "960",
          "UTIL_URAM": "0"
        }
      },
      "convert_axis_to_net_axis_512_1": {
        "Latency": {
          "LatencyBest": "1",
          "LatencyAvg": "1",
          "LatencyWorst": "1",
          "PipelineII": "1",
          "PipelineDepth": "2",
          "PipelineType": "yes"
        },
        "Timing": {
          "Target": "3.20",
          "Uncertainty": "0.86",
          "Estimate": "1.168"
        },
        "Area": {
          "FF": "581",
          "AVAIL_FF": "2607360",
          "UTIL_FF": "~0",
          "LUT": "37",
          "AVAIL_LUT": "1303680",
          "UTIL_LUT": "~0",
          "BRAM_18K": "0",
          "AVAIL_BRAM": "4032",
          "UTIL_BRAM": "0",
          "DSP": "0",
          "AVAIL_DSP": "9024",
          "UTIL_DSP": "0",
          "URAM": "0",
          "AVAIL_URAM": "960",
          "UTIL_URAM": "0"
        }
      },
      "convert_net_axis_to_axis_512_s": {
        "Latency": {
          "LatencyBest": "2",
          "LatencyAvg": "2",
          "LatencyWorst": "2",
          "PipelineII": "1",
          "PipelineDepth": "3",
          "PipelineType": "yes"
        },
        "Timing": {
          "Target": "3.20",
          "Uncertainty": "0.86",
          "Estimate": "1.168"
        },
        "Area": {
          "FF": "583",
          "AVAIL_FF": "2607360",
          "UTIL_FF": "~0",
          "LUT": "43",
          "AVAIL_LUT": "1303680",
          "UTIL_LUT": "~0",
          "BRAM_18K": "0",
          "AVAIL_BRAM": "4032",
          "UTIL_BRAM": "0",
          "DSP": "0",
          "AVAIL_DSP": "9024",
          "UTIL_DSP": "0",
          "URAM": "0",
          "AVAIL_URAM": "960",
          "UTIL_URAM": "0"
        }
      },
      "convert_net_axis_to_axis_512_1": {
        "Latency": {
          "LatencyBest": "2",
          "LatencyAvg": "2",
          "LatencyWorst": "2",
          "PipelineII": "1",
          "PipelineDepth": "3",
          "PipelineType": "yes"
        },
        "Timing": {
          "Target": "3.20",
          "Uncertainty": "0.86",
          "Estimate": "1.168"
        },
        "Area": {
          "FF": "583",
          "AVAIL_FF": "2607360",
          "UTIL_FF": "~0",
          "LUT": "43",
          "AVAIL_LUT": "1303680",
          "UTIL_LUT": "~0",
          "BRAM_18K": "0",
          "AVAIL_BRAM": "4032",
          "UTIL_BRAM": "0",
          "DSP": "0",
          "AVAIL_DSP": "9024",
          "UTIL_DSP": "0",
          "URAM": "0",
          "AVAIL_URAM": "960",
          "UTIL_URAM": "0"
        }
      },
      "process_ipv4_512_s": {
        "Latency": {
          "LatencyBest": "2",
          "LatencyAvg": "2",
          "LatencyWorst": "2",
          "PipelineII": "1",
          "PipelineDepth": "3",
          "PipelineType": "yes"
        },
        "Timing": {
          "Target": "3.20",
          "Uncertainty": "0.86",
          "Estimate": "2.220"
        },
        "Area": {
          "FF": "1216",
          "AVAIL_FF": "2607360",
          "UTIL_FF": "~0",
          "LUT": "1583",
          "AVAIL_LUT": "1303680",
          "UTIL_LUT": "~0",
          "BRAM_18K": "0",
          "AVAIL_BRAM": "4032",
          "UTIL_BRAM": "0",
          "DSP": "0",
          "AVAIL_DSP": "9024",
          "UTIL_DSP": "0",
          "URAM": "0",
          "AVAIL_URAM": "960",
          "UTIL_URAM": "0"
        }
      },
      "ipv4_drop_optional_ip_header_512_s": {
        "Latency": {
          "LatencyBest": "1",
          "LatencyAvg": "1",
          "LatencyWorst": "1",
          "PipelineII": "1",
          "PipelineDepth": "2",
          "PipelineType": "yes"
        },
        "Timing": {
          "Target": "3.20",
          "Uncertainty": "0.86",
          "Estimate": "3.114"
        },
        "Area": {
          "FF": "3950",
          "AVAIL_FF": "2607360",
          "UTIL_FF": "~0",
          "LUT": "230",
          "AVAIL_LUT": "1303680",
          "UTIL_LUT": "~0",
          "BRAM_18K": "0",
          "AVAIL_BRAM": "4032",
          "UTIL_BRAM": "0",
          "DSP": "0",
          "AVAIL_DSP": "9024",
          "UTIL_DSP": "0",
          "URAM": "0",
          "AVAIL_URAM": "960",
          "UTIL_URAM": "0"
        }
      },
      "ipv4_lshiftWordByOctet_512_2_s": {
        "Latency": {
          "LatencyBest": "1",
          "LatencyAvg": "1",
          "LatencyWorst": "1",
          "PipelineII": "1",
          "PipelineDepth": "2",
          "PipelineType": "yes"
        },
        "Timing": {
          "Target": "3.20",
          "Uncertainty": "0.86",
          "Estimate": "2.399"
        },
        "Area": {
          "FF": "1161",
          "AVAIL_FF": "2607360",
          "UTIL_FF": "~0",
          "LUT": "593",
          "AVAIL_LUT": "1303680",
          "UTIL_LUT": "~0",
          "BRAM_18K": "0",
          "AVAIL_BRAM": "4032",
          "UTIL_BRAM": "0",
          "DSP": "0",
          "AVAIL_DSP": "9024",
          "UTIL_DSP": "0",
          "URAM": "0",
          "AVAIL_URAM": "960",
          "UTIL_URAM": "0"
        }
      },
      "ipv4_generate_ipv4_512_s": {
        "Latency": {
          "LatencyBest": "1",
          "LatencyAvg": "1",
          "LatencyWorst": "1",
          "PipelineII": "1",
          "PipelineDepth": "2",
          "PipelineType": "yes"
        },
        "Timing": {
          "Target": "3.20",
          "Uncertainty": "0.86",
          "Estimate": "1.866"
        },
        "Area": {
          "FF": "2298",
          "AVAIL_FF": "2607360",
          "UTIL_FF": "~0",
          "LUT": "240",
          "AVAIL_LUT": "1303680",
          "UTIL_LUT": "~0",
          "BRAM_18K": "0",
          "AVAIL_BRAM": "4032",
          "UTIL_BRAM": "0",
          "DSP": "0",
          "AVAIL_DSP": "9024",
          "UTIL_DSP": "0",
          "URAM": "0",
          "AVAIL_URAM": "960",
          "UTIL_URAM": "0"
        }
      },
      "ipv4_top": {
        "Latency": {
          "LatencyBest": "6",
          "LatencyAvg": "6",
          "LatencyWorst": "6",
          "PipelineII": "1",
          "PipelineDepth": "",
          "PipelineType": "dataflow"
        },
        "Timing": {
          "Target": "3.20",
          "Uncertainty": "0.86",
          "Estimate": "3.114"
        },
        "Area": {
          "BRAM_18K": "0",
          "AVAIL_BRAM": "4032",
          "UTIL_BRAM": "0",
          "FF": "25389",
          "AVAIL_FF": "2607360",
          "UTIL_FF": "~0",
          "LUT": "10288",
          "AVAIL_LUT": "1303680",
          "UTIL_LUT": "~0",
          "DSP": "0",
          "AVAIL_DSP": "9024",
          "UTIL_DSP": "0",
          "URAM": "0",
          "AVAIL_URAM": "960",
          "UTIL_URAM": "0"
        }
      }
    }
  },
  "GenerateBdFiles": "0",
  "GenData": {
    "DataVersion": "0.2",
    "Time": "2023-03-18 14:34:35 +03",
    "ToolName": "vitis_hls",
    "ToolVersion": "2021.2"
  }
}
